{
  "weekly_data": {
    "monday": [
      {
        "hour": 0,
        "summary": "月曜日の深夜0時。物音はほとんどなく、かすかな寝息が聞こえる。観測対象は静かに睡眠しており、この日の活動や気分を判断できる情報はまだ見られない。全体として、とても落ち着いた状態で1日が始まっている。",
        "burst_events": []
      },
      {
        "hour": 1,
        "summary": "月曜日の深夜1時。引き続き周囲は静かで、穏やかな寝息が続いている。時折小さな寝返りが見られるが、覚醒の兆候はない。観測対象は安心した状態で眠っており、情緒は安定していると考えられる。",
        "burst_events": []
      },
      {
        "hour": 2,
        "summary": "月曜日の深夜2時。大きな物音はなく、静かな睡眠が続いている。ときどき寝言のような声が聞こえるが、内容は判別できない。全体として、のんびりとした性質がそのまま睡眠にも表れている印象がある。",
        "burst_events": []
      },
      {
        "hour": 3,
        "summary": "月曜日の深夜3時。周囲の環境に変化はなく、深い睡眠状態が続いている。体の動きは最小限で、刺激に対する反応も見られない。この時点では、疲労や不安定さを示す兆候は確認されていない。",
        "burst_events": []
      },
      {
        "hour": 4,
        "summary": "月曜日の早朝4時。静かな環境の中で睡眠が継続している。呼吸は一定で、落ち着いた状態が保たれている。観測対象の穏やかな気質が、そのまま安定した睡眠として現れている。",
        "burst_events": []
      },
      {
        "hour": 5,
        "summary": "月曜日の早朝5時。睡眠状態に大きな変化はなく、引き続き静かな時間が流れている。外部刺激への反応はほとんど見られず、安心して休めている様子がうかがえる。ここまで、この日はとても穏やかな立ち上がりを迎えている。",
        "burst_events": []
      },
      {
        "hour": 6,
        "summary": "月曜日の朝6時。まだ眠りの状態が続いており、はっきりとした覚醒は見られない。かすかな物音に一瞬反応する様子はあるが、再び静かな呼吸に戻っている。この時点では、ゆっくりとした目覚めになりそうな気配がある。",
        "burst_events": []
      },
      {
        "hour": 7,
        "summary": "月曜日の朝7時。夜間は大きな物音もなく、全体として安定した睡眠が続いていた。やや眠気を残した状態で起床し、朝の支度はゆっくりとしたペースで進んでいる。起床直後は反応が鈍く、全体的にテンションは低めだが、混乱や強い拒否は見られない。朝食を取り始めると、少しずつ表情や反応が戻り始めている。この時点では、静かな立ち上がりの朝を迎えていると整理できる。",
        "burst_events": []
      },
      {
        "hour": 8,
        "summary": "月曜日の朝8時。起床後は眠気の強い状態から始まったが、朝食を取るにつれて徐々に反応が安定してきた。その流れのまま登園の支度に入り、バス停へ向かう場面では気持ちが外に切り替わり始めている。依然としてハイテンションではないものの、不安定さは見られず、落ち着いた状態で行動できている。朝の立ち上がりは緩やかだが、日常のリズムには無理なく戻りつつある。この時点では、穏やかな朝の経過がこの日の基調になっている。",
        "burst_events": []
      },
      {
        "hour": 9,
        "summary": "月曜日の朝9時。朝は眠気の残る静かな立ち上がりだったが、登園をきっかけに外の環境へ気持ちが切り替わり始めている。まだテンションは控えめだが、不安定さはなく、落ち着いて行動できている。人や音のある環境に入っても大きな緊張は見られず、ゆっくりと調子を上げていく流れができつつある。この時点では、穏やかなペースで1日が進み始めていると整理できる。",
        "burst_events": []
      },
      {
        "hour": 10,
        "summary": "月曜日の午前10時。朝の低めのテンションからは回復し、園での活動に自然に入り込めている。自分のペースを保ちながら周囲の流れに乗れており、過度な興奮や萎縮は見られない。落ち着いた集中状態が続いており、この日は静かに調子を上げていくタイプの午前になっている。ここまでの流れを見ると、無理のない安定した午前を過ごしていると捉えられる。",
        "burst_events": []
      },
      {
        "hour": 11,
        "summary": "月曜日の午前11時。午前中の活動が進む中で、身体を動かす場面が増え、全体の活性ははっきりと高まってきている。朝のスロースタートとは対照的に、現在は表現や反応が豊かになっている。ただし興奮が先行しすぎる様子はなく、楽しさが素直に外に出ている印象である。この時点では、午前中は良い形でエネルギーが引き出されている流れといえる。",
        "burst_events": [
          {
            "time": "11:00",
            "event": "身体を動かす遊びでテンションが上がる。声量や動きが大きくなる。",
            "score_change": 40
          }
        ]
      },
      {
        "hour": 12,
        "summary": "月曜日の正午12時。午前中に高まった活動量の後、気持ちは落ち着き、情緒は安定した状態に入っている。刺激に対する反応は穏やかで、安心感のある時間帯になっている。朝から続いていた緊張や眠気はすでに見られず、この日の中で最も安定した時間のひとつとして整理できる。午前から昼にかけて、全体として良いリズムが保たれている。",
        "burst_events": [
          {
            "time": "11:00",
            "event": "身体を動かす遊びでテンションが上がる。声量や動きが大きくなる。",
            "score_change": 40
          }
        ]
      },
      {
        "hour": 13,
        "summary": "月曜日の午後1時。午前中の活動を経て、少しずつ疲労の兆しが見え始めている。大きな乱れはないが、反応の速さや集中の持続にはばらつきが出てきている。とはいえ、情緒は引き続き安定しており、安心できる環境の中で過ごせている。この時点では、午前の充実感と午後への移行が同時に存在している状態といえる。",
        "burst_events": [
          {
            "time": "11:00",
            "event": "身体を動かす遊びでテンションが上がる。声量や動きが大きくなる。",
            "score_change": 40
          }
        ]
      },
      {
        "hour": 14,
        "summary": "月曜日の午後2時。疲れが少しずつ前面に出始め、集中の波が短くなってきている。朝から積み上がってきた活動量を考えると、自然な変化として受け取れる範囲である。大きな感情の揺れや崩れは見られず、全体としては落ち着いたまま推移している。この日の前半が穏やかに進んできたことが、午後の安定にもつながっている。",
        "burst_events": [
          {
            "time": "11:00",
            "event": "身体を動かす遊びでテンションが上がる。声量や動きが大きくなる。",
            "score_change": 40
          }
        ]
      },
      {
        "hour": 15,
        "summary": "月曜日の午後3時。午前中の活発さから一転し、はっきりと疲労が表に出てきている。反応はゆっくりになり、刺激に対する耐性も下がってきているが、大きな混乱や感情の崩れは見られない。朝のスロースタートから午前の充実、そして午後の疲れへと、1日の流れは一貫して自然に推移している。この時点では、無理のない範囲で1日を過ごしてきた様子が読み取れる。",
        "burst_events": [
          {
            "time": "11:00",
            "event": "身体を動かす遊びでテンションが上がる。声量や動きが大きくなる。",
            "score_change": 40
          }
        ]
      },
      {
        "hour": 16,
        "summary": "月曜日の午後4時。園での活動を終え、安心できる環境に戻ったことで気持ちははっきりと落ち着いてきている。午後に見られていた疲労感は残っているものの、緊張が解け、表情や反応には余裕が戻ってきている。この日は、外の環境で無理を重ねるよりも、切り替えによって回復できるタイプの流れが見えてきている。ここまでを見ると、環境の変化が情緒の安定に大きく寄与している1日といえる。",
        "burst_events": [
          {
            "time": "11:00",
            "event": "身体を動かす遊びでテンションが上がる。声量や動きが大きくなる。",
            "score_change": 40
          },
          {
            "time": "16:00",
            "event": "帰宅。安心できる環境に戻り、表情が緩む。",
            "score_change": 54
          }
        ]
      },
      {
        "hour": 17,
        "summary": "帰宅後はおやつを取り、その後は自分の好きな遊びに自然に入り込めている。園での疲れは残っているが、静かに集中できる遊びを選んでおり、気持ちの立て直しが進んでいる。興奮が強く出るというよりは、安心感の中でエネルギーが戻ってきている印象である。この時点では、この日は『回復の仕方が穏やかな日』としての輪郭がよりはっきりしてきている。",
        "burst_events": [
          {
            "time": "11:00",
            "event": "身体を動かす遊びでテンションが上がる。声量や動きが大きくなる。",
            "score_change": 40
          },
          {
            "time": "16:00",
            "event": "帰宅。安心できる環境に戻り、表情が緩む。",
            "score_change": 54
          },
          {
            "time": "17:00",
            "event": "好きな遊びに没頭する時間。集中と興奮が混ざった状態。",
            "score_change": 35
          }
        ]
      },
      {
        "hour": 18,
        "summary": "夕方に入り、家庭内での時間が続く中で、全体のテンションは落ち着いた水準で安定している。遊びを楽しみながらも、午後に蓄積した疲労は少しずつ表に出始めており、活動量は自然に抑えられている。無理に気分を上げようとする様子はなく、自分のペースを守れている点がこの日の特徴として読み取れる。この時点では、1日の活動がゆっくりと収束に向かい始めている。",
        "burst_events": [
          {
            "time": "11:00",
            "event": "身体を動かす遊びでテンションが上がる。声量や動きが大きくなる。",
            "score_change": 40
          },
          {
            "time": "16:00",
            "event": "帰宅。安心できる環境に戻り、表情が緩む。",
            "score_change": 54
          },
          {
            "time": "17:00",
            "event": "好きな遊びに没頭する時間。集中と興奮が混ざった状態。",
            "score_change": 35
          },
          {
            "time": "18:00",
            "event": "夕方になり徐々に疲れが表に出る。指示への反応が遅くなる。",
            "score_change": -53
          }
        ]
      },
      {
        "hour": 19,
        "summary": "家族との夕食を迎え、気持ちは再び安定した状態に整っている。朝の眠気から始まり、午前の活動、午後の疲れ、そして帰宅後の回復という流れが、この時間帯ではひとつのまとまりとして見えてきた。大きな感情の乱れはなく、切り替えを重ねながら穏やかに1日を過ごしてきた様子が明確になっている。この日の全体像は、静かな始まりと穏やかな回復を特徴とする1日として整理できる。",
        "burst_events": [
          {
            "time": "11:00",
            "event": "身体を動かす遊びでテンションが上がる。声量や動きが大きくなる。",
            "score_change": 40
          },
          {
            "time": "16:00",
            "event": "帰宅。安心できる環境に戻り、表情が緩む。",
            "score_change": 54
          },
          {
            "time": "17:00",
            "event": "好きな遊びに没頭する時間。集中と興奮が混ざった状態。",
            "score_change": 35
          },
          {
            "time": "18:00",
            "event": "夕方になり徐々に疲れが表に出る。指示への反応が遅くなる。",
            "score_change": -53
          }
        ]
      },
      {
        "hour": 20,
        "summary": "月曜日は、眠気の残る静かな朝から始まった。起床直後は反応がゆっくりで、朝の支度も落ち着いたペースだったが、朝食をきっかけに徐々に調子が戻っていった。登園後は無理のない形で活動に入り、午前中は自分のペースを保ちながら安定して過ごしている。午後は活動の積み重ねによる疲れが見られたものの、大きな感情の乱れはなく、帰宅後は安心できる環境の中で回復が進んだ。現在は歯磨きや家族との学習を終え、1日を穏やかに終える準備が整っている。",
        "burst_events": [
          {
            "time": "11:00",
            "event": "身体を動かす遊びでテンションが上がる。声量や動きが大きくなる。",
            "score_change": 40
          },
          {
            "time": "16:00",
            "event": "帰宅。安心できる環境に戻り、表情が緩む。",
            "score_change": 54
          },
          {
            "time": "17:00",
            "event": "好きな遊びに没頭する時間。集中と興奮が混ざった状態。",
            "score_change": 35
          },
          {
            "time": "18:00",
            "event": "夕方になり徐々に疲れが表に出る。指示への反応が遅くなる。",
            "score_change": -53
          }
        ]
      },
      {
        "hour": 21,
        "summary": "月曜日は、スロースタートの朝から始まり、日中にかけて少しずつ活動量が増えていった。午前中は落ち着いた集中が続き、午後には疲れが表に出たが、強い混乱や不安定さは見られていない。帰宅後は自分の好きな遊びを通して気持ちを整え、家庭内で安定した時間を過ごしてきた。夜は歯磨きや学習といった日課をこなし、無理なく就寝に向かっている。この日は全体として、環境の切り替えによって安定を保てた1日だった。",
        "burst_events": [
          {
            "time": "11:00",
            "event": "身体を動かす遊びでテンションが上がる。声量や動きが大きくなる。",
            "score_change": 40
          },
          {
            "time": "16:00",
            "event": "帰宅。安心できる環境に戻り、表情が緩む。",
            "score_change": 54
          },
          {
            "time": "17:00",
            "event": "好きな遊びに没頭する時間。集中と興奮が混ざった状態。",
            "score_change": 35
          },
          {
            "time": "18:00",
            "event": "夕方になり徐々に疲れが表に出る。指示への反応が遅くなる。",
            "score_change": -53
          }
        ]
      },
      {
        "hour": 22,
        "summary": "月曜日は、朝の眠気を引きずりながらも、時間の経過とともに自然に調子を上げていった1日だった。午前中は穏やかに活動へ入り、午後には疲労が見られたが、大きな感情の上下はなく推移している。帰宅後は安心できる環境で回復し、静かに集中できる遊びや家族との関わりを通して気持ちを整えた。夜は決まった流れで就寝準備が進み、現在は安定した状態で休息に入っている。この日は、自分のペースを守りながら過ごせた日として整理できる。",
        "burst_events": [
          {
            "time": "11:00",
            "event": "身体を動かす遊びでテンションが上がる。声量や動きが大きくなる。",
            "score_change": 40
          },
          {
            "time": "16:00",
            "event": "帰宅。安心できる環境に戻り、表情が緩む。",
            "score_change": 54
          },
          {
            "time": "17:00",
            "event": "好きな遊びに没頭する時間。集中と興奮が混ざった状態。",
            "score_change": 35
          },
          {
            "time": "18:00",
            "event": "夕方になり徐々に疲れが表に出る。指示への反応が遅くなる。",
            "score_change": -53
          }
        ]
      },
      {
        "hour": 23,
        "summary": "月曜日は、眠気の残る穏やかな朝から始まり、日中にかけて少しずつ活動が広がっていった。午前中は落ち着いた集中が見られ、午後には疲れが出たものの、感情が大きく崩れる場面はなかった。帰宅後は家庭での安心感の中で回復し、自分の好きな遊びや家族との時間を通して気持ちを整えている。夜は日課に沿って静かに過ごし、そのまま無理なく就寝に入った。全体として、この日は刺激に振り回されることなく、切り替えを重ねながら穏やかに完結した1日だった。",
        "burst_events": [
          {
            "time": "11:00",
            "event": "身体を動かす遊びでテンションが上がる。声量や動きが大きくなる。",
            "score_change": 40
          },
          {
            "time": "16:00",
            "event": "帰宅。安心できる環境に戻り、表情が緩む。",
            "score_change": 54
          },
          {
            "time": "17:00",
            "event": "好きな遊びに没頭する時間。集中と興奮が混ざった状態。",
            "score_change": 35
          },
          {
            "time": "18:00",
            "event": "夕方になり徐々に疲れが表に出る。指示への反応が遅くなる。",
            "score_change": -53
          }
        ]
      }
    ]
  }
}